odoo/addons/fs_storage_ms_drive/README.rst
odoo/addons/fs_storage_ms_drive/__init__.py
odoo/addons/fs_storage_ms_drive/__manifest__.py
odoo/addons/fs_storage_ms_drive/i18n/fs_storage_ms_drive.pot
odoo/addons/fs_storage_ms_drive/i18n/it.po
odoo/addons/fs_storage_ms_drive/models/__init__.py
odoo/addons/fs_storage_ms_drive/models/fs_storage.py
odoo/addons/fs_storage_ms_drive/models/res_user.py
odoo/addons/fs_storage_ms_drive/readme/CONTRIBUTORS.md
odoo/addons/fs_storage_ms_drive/readme/CREDITS.md
odoo/addons/fs_storage_ms_drive/readme/DESCRIPTION.md
odoo/addons/fs_storage_ms_drive/static/description/icon.png
odoo/addons/fs_storage_ms_drive/static/description/index.html
odoo_addon_fs_storage_ms_drive-18.0.1.0.0.7.dist-info/METADATA
odoo_addon_fs_storage_ms_drive-18.0.1.0.0.7.dist-info/WHEEL
odoo_addon_fs_storage_ms_drive-18.0.1.0.0.7.dist-info/top_level.txt
odoo_addon_fs_storage_ms_drive-18.0.1.0.0.7.dist-info/RECORD
