Metadata-Version: 2.1
Name: odoo-addon-fs_storage_ms_drive
Version: 18.0.1.0.0.7
Requires-Python: >=3.10
Requires-Dist: fsspec>=2025.0.0
Requires-Dist: msgraphfs
Requires-Dist: odoo-addon-fs_storage==18.0.*
Requires-Dist: odoo-addon-microsoft_drive_account==18.0.*
Requires-Dist: odoo==18.0.*
Summary: Add the microsoft drives (OneDrive, Sharepoint) as a storage backend
Home-page: https://github.com/OCA/storage
License: LGPL-3
Author: ACSONE SA/NV, Odoo Community Association (OCA)
Author-email: support@odoo-community.org
Classifier: Programming Language :: Python
Classifier: Framework :: Odoo
Classifier: Framework :: Odoo :: 18.0
Classifier: License :: OSI Approved :: GNU Lesser General Public License v3 (LGPLv3)
Classifier: Development Status :: 4 - Beta
